fastarch/__init__.py
fastarch/main.py
fastarch/management/__init__.py
fastarch/management/commands/__init__.py
fastarch/management/commands/add_entity.py
fastarch/management/commands/base_command.py
fastarch/management/commands/create_project.py
fastarch/management/manager.py
fastarch-0.0.0.dist-info/LICENSE
fastarch-0.0.0.dist-info/METADATA
fastarch-0.0.0.dist-info/WHEEL
fastarch-0.0.0.dist-info/entry_points.txt
fastarch-0.0.0.dist-info/RECORD
